{
    "author": "root",
    "title": "Worlds Together Worlds Apart Chapters 9",
    "description": "Review set for Mr Diffley's World History class",
    "list": [
        {
            "name": "Khadija",
            "definition": "Muhammad's wife, a wealthy widow who ran a prosperous caravan business"
        },
        {
            "name": "Abu Bakr",
            "definition": "Muhammad's father-in-law and early convert to Islam who became the first caliph"
        },
        {
            "name": "Ali",
            "definition": "Muhammad's cousin and son-in-law who was assassinated after becoming the fourth caliph, trusted by Shi'ites"
        },
        {
            "name": "Abd al-Rahman",
            "definition": "Umayyad prince who escaped the Abbasid massacre of his family and fled to Spain to establish a new Umayyad dynasty"
        },
        {
            "name": "Abu al-Abbas",
            "definition": "Descendant of Muhammad's uncle who led a rebellion against the Umayyads and founded the Abbasid dynasty"
        },
        {
            "name": "al-Shafi’l",
            "definition": "Iraqi Ulama, Muslim theologian who established the basis for Islamic law. Said Hadith should be based off of Muhammad's teaching."
        },
        {
            "name": "al-Khwarizimi",
            "definition": "Muslim mathematician who pioneered the study of algebra"
        },
        {
            "name": "Ibn Sina (Avicenna)",
            "definition": "Muslim-Persian physician who wrote the Canon on Medicine"
        }
    ]
}
